<?xml version="1.0" encoding="utf-8" ?>
<hibernate-mapping xmlns="urn:nhibernate-mapping-2.2"
                   assembly="MultiAlignCore"
                   namespace="MultiAlignCore.Data">

  <class name="ScanSummary" table="T_ScanSummaries" lazy="false">
    <composite-id>
      <key-property name="Scan"               column="Scan_Num"             type="int" />
      <key-property name="DatasetId"          column="Dataset_ID"           type="int" />
    </composite-id>
    <property name="Time"                     column="Time"                 type="double" not-null="false" />
    <property name="MsLevel"                  column="MS_Level"             type="int"    not-null="false" />
    <property name="TotalIonCurrent"          column="Total_Ion_Current"    type="double" not-null="false" />
    <property name="NumberOfPeaks"            column="Number_of_Peaks"      type="double" not-null="false" />
    <property name="NumberOfDeisotoped"       column="Number_of_Deisotoped"  type="double" not-null="false" />
    <property name="PrecursorMz"              column="Precursor_Mz"         type="double" not-null="false" />
    <property name="Bpi"                      column="Base_peak_intensity"  type="double" not-null="false" />
    <property name="BpiMz"                    column="Base_peak_Mz"         type="double" not-null="false" />
    <property name="CollisionType"            column="Collision_Type"/>
  </class>
</hibernate-mapping>
